PySide6-stubs/__init__.pyi
PySide6-stubs/Qt3DAnimation/_Qt3DAnimation.pyi
PySide6-stubs/Qt3DAnimation/__init__.pyi
PySide6-stubs/Qt3DAnimation/_functions.pyi
PySide6-stubs/Qt3DCore/_Qt3DCore.pyi
PySide6-stubs/Qt3DCore/__init__.pyi
PySide6-stubs/Qt3DCore/_functions.pyi
PySide6-stubs/Qt3DExtras/_Qt3DExtras.pyi
PySide6-stubs/Qt3DExtras/__init__.pyi
PySide6-stubs/Qt3DExtras/_functions.pyi
PySide6-stubs/Qt3DInput/_QIntList.pyi
PySide6-stubs/Qt3DInput/_Qt3DInput.pyi
PySide6-stubs/Qt3DInput/__init__.pyi
PySide6-stubs/Qt3DInput/_functions.pyi
PySide6-stubs/Qt3DLogic/_Qt3DLogic.pyi
PySide6-stubs/Qt3DLogic/__init__.pyi
PySide6-stubs/Qt3DLogic/_functions.pyi
PySide6-stubs/Qt3DRender/_QIntList.pyi
PySide6-stubs/Qt3DRender/_Qt3DRender.pyi
PySide6-stubs/Qt3DRender/__init__.pyi
PySide6-stubs/Qt3DRender/_functions.pyi
PySide6-stubs/QtAxContainer/_QAxBase.pyi
PySide6-stubs/QtAxContainer/_QAxBaseObject.pyi
PySide6-stubs/QtAxContainer/_QAxBaseWidget.pyi
PySide6-stubs/QtAxContainer/_QAxObject.pyi
PySide6-stubs/QtAxContainer/_QAxObjectInterface.pyi
PySide6-stubs/QtAxContainer/_QAxScript.pyi
PySide6-stubs/QtAxContainer/_QAxScriptEngine.pyi
PySide6-stubs/QtAxContainer/_QAxScriptManager.pyi
PySide6-stubs/QtAxContainer/_QAxSelect.pyi
PySide6-stubs/QtAxContainer/_QAxWidget.pyi
PySide6-stubs/QtAxContainer/__init__.pyi
PySide6-stubs/QtAxContainer/_functions.pyi
PySide6-stubs/QtBluetooth/_QBluetooth.pyi
PySide6-stubs/QtBluetooth/_QBluetoothAddress.pyi
PySide6-stubs/QtBluetooth/_QBluetoothDeviceDiscoveryAgent.pyi
PySide6-stubs/QtBluetooth/_QBluetoothDeviceInfo.pyi
PySide6-stubs/QtBluetooth/_QBluetoothHostInfo.pyi
PySide6-stubs/QtBluetooth/_QBluetoothLocalDevice.pyi
PySide6-stubs/QtBluetooth/_QBluetoothServer.pyi
PySide6-stubs/QtBluetooth/_QBluetoothServiceDiscoveryAgent.pyi
PySide6-stubs/QtBluetooth/_QBluetoothServiceInfo.pyi
PySide6-stubs/QtBluetooth/_QBluetoothSocket.pyi
PySide6-stubs/QtBluetooth/_QBluetoothUuid.pyi
PySide6-stubs/QtBluetooth/_QLowEnergyAdvertisingData.pyi
IceSpringPySideStubs_PySide6-1.3.1.dist-info/METADATA
IceSpringPySideStubs_PySide6-1.3.1.dist-info/WHEEL
IceSpringPySideStubs_PySide6-1.3.1.dist-info/top_level.txt
IceSpringPySideStubs_PySide6-1.3.1.dist-info/RECORD
